cos_eval_tf_metrics/__init__.py
cos_eval_tf_metrics/metrics.py
cos_eval_tf_metrics-0.0.1.dist-info/licenses/LICENSE
cos_eval_tf_metrics-0.0.1.dist-info/METADATA
cos_eval_tf_metrics-0.0.1.dist-info/WHEEL
cos_eval_tf_metrics-0.0.1.dist-info/top_level.txt
cos_eval_tf_metrics-0.0.1.dist-info/RECORD
